{
  "schema": "https://sibyl.os/schemas/capsule/v0",
  "name": "hello-capsule",
  "version": "0.1.0",
  "title": "Hello, Capsule",
  "description": "The smallest real instant capsule: counts its runs via the storage.local capability.",
  "kind": "instant",
  "entry": "index.html",
  "apk": null,
  "runtime": { "engine": "web", "min": "0.1.0" },
  "capabilities": ["storage.local"],
  "trust": {
    "minLevel": "L1",
    "passport": "passport.json",
    "signature": null,
    "publisherKey": null
  },
  "source": {
    "repo": "https://github.com/Costder/Capsule-Market-and-Sibyl-OS",
    "fork_of": null,
    "license": "MIT"
  },
  "ui": { "icon": null, "screenshots": [], "demo": null }
}
